[
  {
    "Result": "Airbagon",
    "Parent1": "Toady",
    "Parent2": "Killer Gila"
  },
  {
    "Result": "Angel Slime",
    "Parent1": "Mitey Oak",
    "Parent2": "Healslime"
  },
  {
    "Result": "Angel Slime",
    "Parent1": "Slime Family (E)",
    "Parent2": "Nature Family (E)"
  },
  {
    "Result": "Armoured Wartoise",
    "Parent1": "Bongo Drongo",
    "Parent2": "Dragonthorn"
  },
  {
    "Result": "Armoured Wartoise",
    "Parent1": "Dragon Family (F)",
    "Parent2": "Material Family (F)"
  },
  {
    "Result": "Avian Android",
    "Parent1": "Mecha-Mynah",
    "Parent2": "Damselfly"
  },
  {
    "Result": "Avian Android",
    "Parent1": "Nature Family (F)",
    "Parent2": "Material Family (F)"
  },
  {
    "Result": "Avian Android",
    "Parent1": "Ornery Onion",
    "Parent2": "Mecha-Mynah"
  },
  {
    "Result": "Awebergine",
    "Parent1": "Pogoin' Penguin",
    "Parent2": "Woebergine"
  },
  {
    "Result": "Bag o' Laughs",
    "Parent1": "Slime Family (G)",
    "Parent2": "Material Family (G)"
  },
  {
    "Result": "Bagworm",
    "Parent1": "Beast Family (F)",
    "Parent2": "Nature Family (F)"
  },
  {
    "Result": "Bagworm",
    "Parent1": "Stump Chump",
    "Parent2": "Eggsoskeleton"
  },
  {
    "Result": "Bambooligan",
    "Parent1": "String Fella",
    "Parent2": "Eggsoskeleton"
  },
  {
    "Result": "Beanie Meanie",
    "Parent1": "Cruelcumber",
    "Parent2": "Odd Cob"
  },
  {
    "Result": "Behemoth Slime",
    "Parent1": "Slime",
    "Parent2": "Jargon"
  },
  {
    "Result": "Behemoth Slime",
    "Parent1": "Slime Family (E)",
    "Parent2": "Dragon Family (E)"
  },
  {
    "Result": "Beleth",
    "Parent1": "Demon Family (E)",
    "Parent2": "Dragon Family (E)"
  },
  {
    "Result": "Beleth",
    "Parent1": "Erazor Blade",
    "Parent2": "Dancing Devil"
  },
  {
    "Result": "Blinkster",
    "Parent1": "Winky",
    "Parent2": "Ghost"
  },
  {
    "Result": "Bludgerigar",
    "Parent1": "Beast Family (G)",
    "Parent2": "Nature Family (G)"
  },
  {
    "Result": "Bodkin Archer",
    "Parent1": "Cruelcumber",
    "Parent2": "Picksy"
  },
  {
    "Result": "Bodkin Fletcher",
    "Parent1": "Bodkin Archer",
    "Parent2": "Walking Corpse"
  },
  {
    "Result": "Bodkin Fletcher",
    "Parent1": "Demon Family (E)",
    "Parent2": "Beast Family (E)"
  },
  {
    "Result": "Bongo Drongo",
    "Parent1": "Dragon Family (F)",
    "Parent2": "Material Family (F)"
  },
  {
    "Result": "Boppin' Badger",
    "Parent1": "Demon Family (F)",
    "Parent2": "Slime Family (F)"
  },
  {
    "Result": "Boppin' Badger",
    "Parent1": "Mischievous Mole",
    "Parent2": "Vegandragora"
  },
  {
    "Result": "Boppin' Badger",
    "Parent1": "She-Slime",
    "Parent2": "Bunicorn"
  },
  {
    "Result": "Box Slime",
    "Parent1": "She-Slime",
    "Parent2": "Bubble Slime"
  },
  {
    "Result": "Box Slime",
    "Parent1": "She-Slime",
    "Parent2": "Material Family (Any)"
  },
  {
    "Result": "Briny Bronco",
    "Parent1": "Dragon Family (F)",
    "Parent2": "Nature Family (F)"
  },
  {
    "Result": "Briny Bronco",
    "Parent1": "Toady",
    "Parent2": "Small Fry"
  },
  {
    "Result": "Brollygagger",
    "Parent1": "Material Family (E)",
    "Parent2": "Undead Family (E)"
  },
  {
    "Result": "Brownie",
    "Parent1": "Beast Family (E)",
    "Parent2": "Material Family (E)"
  },
  {
    "Result": "Brownie",
    "Parent1": "Hammerhood",
    "Parent2": "Splatypunk"
  },
  {
    "Result": "Bubble Slime",
    "Parent1": "Slimeshroom",
    "Parent2": "Killer Gila"
  },
  {
    "Result": "Buddy Slime",
    "Parent1": "Slime Family (G)",
    "Parent2": "Nature Family (G)"
  },
  {
    "Result": "Bullfinch",
    "Parent1": "Bantamweight",
    "Parent2": "Foo Dog"
  },
  {
    "Result": "Bullfinch",
    "Parent1": "Bantamweight",
    "Parent2": "Beast Family (Any)"
  },
  {
    "Result": "Bunicorn",
    "Parent1": "Fat Rat",
    "Parent2": "Nardragon"
  },
  {
    "Result": "Cactiball",
    "Parent1": "Disfigurine",
    "Parent2": "Nature Family (Any)"
  },
  {
    "Result": "Candy Cat",
    "Parent1": "Fromage Fray",
    "Parent2": "Great Sabrecub"
  },
  {
    "Result": "Cannibox",
    "Parent1": "Bag o' Laughs",
    "Parent2": "Eggsoskeleton"
  },
  {
    "Result": "Cannonbrawler",
    "Parent1": "Demon Family (F)",
    "Parent2": "Material Family (F)"
  },
  {
    "Result": "Capsichum",
    "Parent1": "Nature Family (G)",
    "Parent2": "Material Family (G)"
  },
  {
    "Result": "Cauldragon",
    "Parent1": "Dragon Family (E)",
    "Parent2": "Undead Family (E)"
  },
  {
    "Result": "Cauldragon",
    "Parent1": "Jargon",
    "Parent2": "Killer Gila"
  },
  {
    "Result": "Chimaera",
    "Parent1": "Nature Family (E)",
    "Parent2": "Dragon Family (E)"
  },
  {
    "Result": "Chimaera",
    "Parent1": "Pogoin' Penguin",
    "Parent2": "Imp"
  },
  {
    "Result": "Chocolate Golem",
    "Parent1": "Goonache Goodie",
    "Parent2": "Mud Mannequin"
  },
  {
    "Result": "Chocolate Whisp",
    "Parent1": "Soft Serve Spook",
    "Parent2": "Chocolate Golem"
  },
  {
    "Result": "Chocolate Whisp",
    "Parent1": "Undead Family (E)",
    "Parent2": "Slime Family (E)"
  },
  {
    "Result": "Clockwork Cuckoo",
    "Parent1": "Material Family (E)",
    "Parent2": "Nature Family (E)"
  },
  {
    "Result": "Clockwork Cuckoo",
    "Parent1": "Mecha-Mynah",
    "Parent2": "Cyclown"
  },
  {
    "Result": "Cloud Surfer",
    "Parent1": "Dancing Devil",
    "Parent2": "Cumaulus"
  },
  {
    "Result": "Crabid",
    "Parent1": "Nature Family (E)",
    "Parent2": "Material Family (E)"
  },
  {
    "Result": "Croc-a-Bugle-Doo",
    "Parent1": "Briny Bronco",
    "Parent2": "Bongo Drongo"
  },
  {
    "Result": "Cross Eye",
    "Parent1": "See Urchin",
    "Parent2": "Beast Family (Any)"
  },
  {
    "Result": "Cruelcumber",
    "Parent1": "Bambooligan",
    "Parent2": "Capsichum"
  },
  {
    "Result": "Cumaulus",
    "Parent1": "Nature Family (G)",
    "Parent2": "Material Family (G)"
  },
  {
    "Result": "Cyclown",
    "Parent1": "Nature Family (F)",
    "Parent2": "Demon Family (F)"
  },
  {
    "Result": "Dancing Devil",
    "Parent1": "Demon Family (F)",
    "Parent2": "Undead Family (F)"
  },
  {
    "Result": "Dancing Devil",
    "Parent1": "Gremlin",
    "Parent2": "Undead Family (Any)"
  },
  {
    "Result": "Dark Sabrecub",
    "Parent1": "Beast Family (E)",
    "Parent2": "Slime Family (E)"
  },
  {
    "Result": "Dark Sabrecub",
    "Parent1": "Shadow",
    "Parent2": "Great Sabrecub"
  },
  {
    "Result": "Dark Slime",
    "Parent1": "Imp",
    "Parent2": "Slime Family (Any)"
  },
  {
    "Result": "Dark Slime",
    "Parent1": "Slime Family (E)",
    "Parent2": "Demon Family (E)"
  },
  {
    "Result": "Dark Slime",
    "Parent1": "Succubat",
    "Parent2": "Slime Family (Any)"
  },
  {
    "Result": "Dead Resident",
    "Parent1": "Mummy Boy",
    "Parent2": "Skullrider"
  },
  {
    "Result": "Dessert Demon",
    "Parent1": "Chocolate Golem",
    "Parent2": "Imp"
  },
  {
    "Result": "Disfigurine",
    "Parent1": "String Fella",
    "Parent2": "Dragonthorn"
  },
  {
    "Result": "Drackolyte",
    "Parent1": "Demon Family (E)",
    "Parent2": "Slime Family (E)"
  },
  {
    "Result": "Drackolyte",
    "Parent1": "Whizzard",
    "Parent2": "Dracky"
  },
  {
    "Result": "Drag Racer",
    "Parent1": "Demon Family (F)",
    "Parent2": "Dragon Family (F)"
  },
  {
    "Result": "Drag Racer",
    "Parent1": "Nardragon",
    "Parent2": "Komodo"
  },
  {
    "Result": "Dragonthorn",
    "Parent1": "Dragon Family (G)",
    "Parent2": "Nature Family (G)"
  },
  {
    "Result": "Drake Slime",
    "Parent1": "Slime",
    "Parent2": "Dragon Family (Any)"
  },
  {
    "Result": "Drake Slime",
    "Parent1": "Slime Family (F)",
    "Parent2": "Dragon Family (F)"
  },
  {
    "Result": "Drake Slime",
    "Parent1": "Wing Slime",
    "Parent2": "Small Fry"
  },
  {
    "Result": "Drohl Drone",
    "Parent1": "Demon Family (G)",
    "Parent2": "Undead Family (G)"
  },
  {
    "Result": "Eggsoskeleton",
    "Parent1": "Beast Family (G)",
    "Parent2": "Material Family (G)"
  },
  {
    "Result": "Erazor Blade",
    "Parent1": "Bambooligan",
    "Parent2": "Wax Murderer"
  },
  {
    "Result": "Escudogre",
    "Parent1": "Leery Lout",
    "Parent2": "Hunter Mech"
  },
  {
    "Result": "Escudogre",
    "Parent1": "Material Family (E)",
    "Parent2": "Beast Family (E)"
  },
  {
    "Result": "Fat Rat",
    "Parent1": "Beast Family (G)",
    "Parent2": "Undead Family (G)"
  },
  {
    "Result": "Feral Slime",
    "Parent1": "Slime Family (Any)",
    "Parent2": "Antguzzler"
  },
  {
    "Result": "Feral Slime",
    "Parent1": "Slime Family (F)",
    "Parent2": "Beast Family (F)"
  },
  {
    "Result": "Feralball",
    "Parent1": "Nature Family (G)",
    "Parent2": "Beast Family (G)"
  },
  {
    "Result": "Firespirit",
    "Parent1": "Dragon Family (G)",
    "Parent2": "Undead Family (G)"
  },
  {
    "Result": "Flython",
    "Parent1": "Dragon Family (F)",
    "Parent2": "Undead Family (F)"
  },
  {
    "Result": "Flython",
    "Parent1": "Gremlin",
    "Parent2": "Killer Gila"
  },
  {
    "Result": "Foo Dog",
    "Parent1": "Beast Family (F)",
    "Parent2": "Material Family (F)"
  },
  {
    "Result": "Freezing Fog",
    "Parent1": "Cumaulus",
    "Parent2": "Snowmangler"
  },
  {
    "Result": "Fright Bulb",
    "Parent1": "Slime Family (G)",
    "Parent2": "Demon Family (G)"
  },
  {
    "Result": "Frolicker",
    "Parent1": "Undead Family (E)",
    "Parent2": "Beast Family (E)"
  },
  {
    "Result": "Fromage Fray",
    "Parent1": "Sacksquatch",
    "Parent2": "Ghost"
  },
  {
    "Result": "Funghoul",
    "Parent1": "Stump Chump",
    "Parent2": "Slimeshroom"
  },
  {
    "Result": "Garuda",
    "Parent1": "Pteranodon",
    "Parent2": "Bullfinch"
  },
  {
    "Result": "Ghost",
    "Parent1": "Soft Serve Spook",
    "Parent2": "Sham Hatwitch"
  },
  {
    "Result": "Goodybag",
    "Parent1": "Material Family (E)",
    "Parent2": "Slime Family (E)"
  },
  {
    "Result": "Goodybag",
    "Parent1": "Pogoin' Penguin",
    "Parent2": "Bag o' Laughs"
  },
  {
    "Result": "Goonache Goodie",
    "Parent1": "Fromage Fray",
    "Parent2": "Shell Slime"
  },
  {
    "Result": "Great Sabrecub",
    "Parent1": "Slime Family (G)",
    "Parent2": "Beast Family (G)"
  },
  {
    "Result": "Gremlin",
    "Parent1": "Dragon Family (G)",
    "Parent2": "Demon Family (G)"
  },
  {
    "Result": "Grinferno",
    "Parent1": "Undead Family (E)",
    "Parent2": "Dragon Family (E)"
  },
  {
    "Result": "Guaardvark",
    "Parent1": "Beast Family (F)",
    "Parent2": "Undead Family (F)"
  },
  {
    "Result": "Guaardvark",
    "Parent1": "Bunicorn",
    "Parent2": "Stark Raven"
  },
  {
    "Result": "Ham Shamwitch",
    "Parent1": "Sham Hatwitch",
    "Parent2": "Drake Slime"
  },
  {
    "Result": "Hammerhood",
    "Parent1": "Stump Chump",
    "Parent2": "Mischievous Mole"
  },
  {
    "Result": "Hawk Man",
    "Parent1": "Beast Family (F)",
    "Parent2": "Demon Family (F)"
  },
  {
    "Result": "Hawk Man",
    "Parent1": "Stark Raven",
    "Parent2": "Beast Family (Any)"
  },
  {
    "Result": "Healslime",
    "Parent1": "Wing Slime",
    "Parent2": "Lunatick"
  },
  {
    "Result": "Hell Niño",
    "Parent1": "Cumaulus",
    "Parent2": "Drake Slime"
  },
  {
    "Result": "Hellbound Horror",
    "Parent1": "Demon Family (F)",
    "Parent2": "Undead Family (F)"
  },
  {
    "Result": "Hellbound Horror",
    "Parent1": "Ghost",
    "Parent2": "Bodkin Archer"
  },
  {
    "Result": "Hood",
    "Parent1": "Hammerhood",
    "Parent2": "Mischievous Mole"
  },
  {
    "Result": "Hooper Trooper",
    "Parent1": "Cyclown",
    "Parent2": "Dancing Devil"
  },
  {
    "Result": "Hooper Trooper",
    "Parent1": "Demon Family (E)",
    "Parent2": "Material Family (E)"
  },
  {
    "Result": "Horriflying Saucers",
    "Parent1": "Undead Family (F)",
    "Parent2": "Material Family (F)"
  },
  {
    "Result": "Horriflying Saucers",
    "Parent1": "Wax Murderer",
    "Parent2": "Dracky"
  },
  {
    "Result": "Hunter Mech",
    "Parent1": "Restless Armour",
    "Parent2": "Material Family (Any)"
  },
  {
    "Result": "Imp",
    "Parent1": "Blinkster",
    "Parent2": "Dracky"
  },
  {
    "Result": "Imp",
    "Parent1": "Demon Family (F)",
    "Parent2": "Slime Family (F)"
  },
  {
    "Result": "Iron Maiden",
    "Parent1": "Succubat",
    "Parent2": "Pocus Poppet"
  },
  {
    "Result": "Iron Maiden",
    "Parent1": "Undead Family (E)",
    "Parent2": "Material Family (E)"
  },
  {
    "Result": "Jailcat",
    "Parent1": "Beast Family (E)",
    "Parent2": "Undead Family (E)"
  },
  {
    "Result": "Jailcat",
    "Parent1": "Cannonbrawler",
    "Parent2": "Candy Cat"
  },
  {
    "Result": "Jargon",
    "Parent1": "Airbagon",
    "Parent2": "Beast Family (Any)"
  },
  {
    "Result": "Jargon",
    "Parent1": "Airbagon",
    "Parent2": "Komodo"
  },
  {
    "Result": "Jargon",
    "Parent1": "Beast Family (F)",
    "Parent2": "Dragon Family (F)"
  },
  {
    "Result": "Jinkster",
    "Parent1": "Demon Family (E)",
    "Parent2": "Nature Family (E)"
  },
  {
    "Result": "Jinkster",
    "Parent1": "Pickayune",
    "Parent2": "Blinkster"
  },
  {
    "Result": "Jumping Jackal",
    "Parent1": "Beast Family (E)",
    "Parent2": "Dragon Family (E)"
  },
  {
    "Result": "Jumping Jackal",
    "Parent1": "Orc",
    "Parent2": "Great Sabrecub"
  },
  {
    "Result": "Khalamari Kid",
    "Parent1": "Slime Family (G)",
    "Parent2": "Nature Family (G)"
  },
  {
    "Result": "Killer Gila",
    "Parent1": "Dragon Family (G)",
    "Parent2": "Undead Family (G)"
  },
  {
    "Result": "Killerpillar",
    "Parent1": "Dragon Family (G)",
    "Parent2": "Nature Family (G)"
  },
  {
    "Result": "King Kelp",
    "Parent1": "Scarfish",
    "Parent2": "Woebergine"
  },
  {
    "Result": "Komodo",
    "Parent1": "Dragon Family (G)",
    "Parent2": "Beast Family (G)"
  },
  {
    "Result": "Lampling",
    "Parent1": "Wax Murderer",
    "Parent2": "Spitnik"
  },
  {
    "Result": "Leafy Larrikin",
    "Parent1": "Monolog",
    "Parent2": "Capsichum"
  },
  {
    "Result": "Leery Lout",
    "Parent1": "Demon Family (G)",
    "Parent2": "Material Family (G)"
  },
  {
    "Result": "Lips",
    "Parent1": "Drohl Drone",
    "Parent2": "Toady"
  },
  {
    "Result": "Lumbering Lizard",
    "Parent1": "Dragonthorn",
    "Parent2": "Drag Racer"
  },
  {
    "Result": "Lumbering Lizard",
    "Parent1": "Nature Family (E)",
    "Parent2": "Dragon Family (E)"
  },
  {
    "Result": "Lump Shaman",
    "Parent1": "Demon Family (E)",
    "Parent2": "Undead Family (E)"
  },
  {
    "Result": "Lump Shaman",
    "Parent1": "Lump Wizard",
    "Parent2": "Pocus Poppet"
  },
  {
    "Result": "Lump Wizard",
    "Parent1": "Demon Family (G)",
    "Parent2": "Undead Family (G)"
  },
  {
    "Result": "Lunatick",
    "Parent1": "Nature Family (G)",
    "Parent2": "Demon Family (G)"
  },
  {
    "Result": "Mad Mollusk",
    "Parent1": "Killerpillar",
    "Parent2": "Lips"
  },
  {
    "Result": "Mandrake Major",
    "Parent1": "Dragon Family (E)",
    "Parent2": "Demon Family (E)"
  },
  {
    "Result": "Mandrake Major",
    "Parent1": "Raptile",
    "Parent2": "Restless Armour"
  },
  {
    "Result": "Mecha-Mynah",
    "Parent1": "Dragon Family (G)",
    "Parent2": "Material Family (G)"
  },
  {
    "Result": "Meowgician",
    "Parent1": "Beast Family (E)",
    "Parent2": "Demon Family (E)"
  },
  {
    "Result": "Meowgician",
    "Parent1": "Vampire Cat",
    "Parent2": "Demon Family (Any)"
  },
  {
    "Result": "Merman",
    "Parent1": "Demon Family (F)",
    "Parent2": "Nature Family (F)"
  },
  {
    "Result": "Mischievous Mole",
    "Parent1": "Beast Family (G)",
    "Parent2": "Material Family (G)"
  },
  {
    "Result": "Mitey Oak",
    "Parent1": "Slime Family (F)",
    "Parent2": "Nature Family (F)"
  },
  {
    "Result": "Mitey Oak",
    "Parent1": "Stump Chump",
    "Parent2": "Blinkster"
  },
  {
    "Result": "Monolog",
    "Parent1": "Nature Family (F)",
    "Parent2": "Undead Family (F)"
  },
  {
    "Result": "Monolog",
    "Parent1": "Stump Chump",
    "Parent2": "Lunatick"
  },
  {
    "Result": "Morphean Mushroom",
    "Parent1": "Napir",
    "Parent2": "Funghoul"
  },
  {
    "Result": "Morphean Mushroom",
    "Parent1": "Undead Family (E)",
    "Parent2": "Nature Family (E)"
  },
  {
    "Result": "Mottle Slime",
    "Parent1": "Slime",
    "Parent2": "Beast Family (Any)"
  },
  {
    "Result": "Mouldy Slime",
    "Parent1": "Slime Family (E)",
    "Parent2": "Undead Family (E)"
  },
  {
    "Result": "Mouldy Slime",
    "Parent1": "Slimeshroom",
    "Parent2": "Muddy Hand"
  },
  {
    "Result": "Mouseflap",
    "Parent1": "Fat Rat",
    "Parent2": "Wing Slime"
  },
  {
    "Result": "Mud Mannequin",
    "Parent1": "Sacksquatch",
    "Parent2": "Woebergine"
  },
  {
    "Result": "Muddy Hand",
    "Parent1": "Sacksquatch",
    "Parent2": "Undead Family (Any)"
  },
  {
    "Result": "Muddy Hand",
    "Parent1": "Undead Family (F)",
    "Parent2": "Material Family (F)"
  },
  {
    "Result": "Mudraker",
    "Parent1": "Mud Mannequin",
    "Parent2": "Undead Family (Any)"
  },
  {
    "Result": "Mudraker",
    "Parent1": "Slime Family (F)",
    "Parent2": "Material Family (F)"
  },
  {
    "Result": "Mummy Boy",
    "Parent1": "Walking Corpse",
    "Parent2": "String Fella"
  },
  {
    "Result": "Napir",
    "Parent1": "Beast Family (F)",
    "Parent2": "Material Family (F)"
  },
  {
    "Result": "Nardragon",
    "Parent1": "Dragon Family (G)",
    "Parent2": "Material Family (G)"
  },
  {
    "Result": "Octopot",
    "Parent1": "Nature Family (E)",
    "Parent2": "Demon Family (E)"
  },
  {
    "Result": "Octopot",
    "Parent1": "Orc",
    "Parent2": "Suckling Ocker"
  },
  {
    "Result": "Odd Cob",
    "Parent1": "Cruelcumber",
    "Parent2": "Undead Family (Any)"
  },
  {
    "Result": "Odd Cob",
    "Parent1": "Lunatick",
    "Parent2": "Capsichum"
  },
  {
    "Result": "Odd Cob",
    "Parent1": "Nature Family (F)",
    "Parent2": "Undead Family (F)"
  },
  {
    "Result": "Ogre",
    "Parent1": "Cannonbrawler",
    "Parent2": "Hood"
  },
  {
    "Result": "Onion Slime",
    "Parent1": "Buddy Slime",
    "Parent2": "Ornery Onion"
  },
  {
    "Result": "Onion Slime",
    "Parent1": "Fright Bulb",
    "Parent2": "Nature Family (Any)"
  },
  {
    "Result": "Onion Slime",
    "Parent1": "Slime Family (F)",
    "Parent2": "Nature Family (F)"
  },
  {
    "Result": "Orc",
    "Parent1": "Beast Family (F)",
    "Parent2": "Nature Family (F)"
  },
  {
    "Result": "Orc",
    "Parent1": "Sham Hatwitch",
    "Parent2": "Nature Family (Any)"
  },
  {
    "Result": "Ornery Onion",
    "Parent1": "Nature Family (G)",
    "Parent2": "Demon Family (G)"
  },
  {
    "Result": "Pan Piper",
    "Parent1": "Demon Family (G)",
    "Parent2": "Beast Family (G)"
  },
  {
    "Result": "Peeper",
    "Parent1": "Winky",
    "Parent2": "Pocus Poppet"
  },
  {
    "Result": "Pickayune",
    "Parent1": "Demon Family (F)",
    "Parent2": "Dragon Family (F)"
  },
  {
    "Result": "Pickayune",
    "Parent1": "Picksy",
    "Parent2": "Lampling"
  },
  {
    "Result": "Picksy",
    "Parent1": "Slime Family (G)",
    "Parent2": "Demon Family (G)"
  },
  {
    "Result": "Platypunk",
    "Parent1": "Bludgerigar",
    "Parent2": "Teeny Sanguini"
  },
  {
    "Result": "Pocus Poppet",
    "Parent1": "Demon Family (F)",
    "Parent2": "Material Family (F)"
  },
  {
    "Result": "Pogoin' Penguin",
    "Parent1": "Dragon Family (F)",
    "Parent2": "Nature Family (F)"
  },
  {
    "Result": "Pogoin' Penguin",
    "Parent1": "Stark Raven",
    "Parent2": "Skipper"
  },
  {
    "Result": "Powie Yowie",
    "Parent1": "Platypunk",
    "Parent2": "Demon Family (Any)"
  },
  {
    "Result": "Powie Yowie",
    "Parent1": "Snowmangler",
    "Parent2": "Platypunk"
  },
  {
    "Result": "Prancing Pillar",
    "Parent1": "Lampling",
    "Parent2": "Pocus Poppet"
  },
  {
    "Result": "Pteranodon",
    "Parent1": "Dragon Family (G)",
    "Parent2": "Demon Family (G)"
  },
  {
    "Result": "Puffpoise",
    "Parent1": "Nature Family (E)",
    "Parent2": "Slime Family (E)"
  },
  {
    "Result": "Putrefido",
    "Parent1": "Beast Family (G)",
    "Parent2": "Undead Family (G)"
  },
  {
    "Result": "Raptile",
    "Parent1": "Dragon Family (F)",
    "Parent2": "Slime Family (F)"
  },
  {
    "Result": "Ratatattack",
    "Parent1": "Mouseflap",
    "Parent2": "Guaardvark"
  },
  {
    "Result": "Restless Armour",
    "Parent1": "Slime Knight",
    "Parent2": "Bambooligan"
  },
  {
    "Result": "Robber Rabbit",
    "Parent1": "Bunicorn",
    "Parent2": "Demon Family (Any)"
  },
  {
    "Result": "Robber Rabbit",
    "Parent1": "Mischievous Mole",
    "Parent2": "Bunicorn"
  },
  {
    "Result": "Rockbomb",
    "Parent1": "Material Family (E)",
    "Parent2": "Demon Family (E)"
  },
  {
    "Result": "Rotten Cotton",
    "Parent1": "Feralball",
    "Parent2": "Powie Yowie"
  },
  {
    "Result": "Rubble Slime",
    "Parent1": "Mottle Slime",
    "Parent2": "Mudraker"
  },
  {
    "Result": "Rubble Slime",
    "Parent1": "Slime Family (E)",
    "Parent2": "Material Family (E)"
  },
  {
    "Result": "Sacksquatch",
    "Parent1": "Undead Family (G)",
    "Parent2": "Material Family (G)"
  },
  {
    "Result": "Scallop Slime",
    "Parent1": "Slime Family (G)",
    "Parent2": "Material Family (G)"
  },
  {
    "Result": "Scarfish",
    "Parent1": "Funghoul",
    "Parent2": "Khalamari Kid"
  },
  {
    "Result": "Scarfish",
    "Parent1": "Slime Family (F)",
    "Parent2": "Undead Family (F)"
  },
  {
    "Result": "Scissor Beatle",
    "Parent1": "Nature Family (F)",
    "Parent2": "Material Family (F)"
  },
  {
    "Result": "Scornet",
    "Parent1": "Nature Family (E)",
    "Parent2": "Undead Family (E)"
  },
  {
    "Result": "Scornet",
    "Parent1": "Odd Cob",
    "Parent2": "Scissor Beatle"
  },
  {
    "Result": "See Urchin",
    "Parent1": "Lunatick",
    "Parent2": "Khalamari Kid"
  },
  {
    "Result": "Shadow",
    "Parent1": "Hellbound Horror",
    "Parent2": "Spitnik"
  },
  {
    "Result": "Sham Hatwitch",
    "Parent1": "Beast Family (G)",
    "Parent2": "Dragon Family (G)"
  },
  {
    "Result": "Shell Slime",
    "Parent1": "Slime Family (G)",
    "Parent2": "Beast Family (G)"
  },
  {
    "Result": "She-Slime",
    "Parent1": "Slime",
    "Parent2": "Firespirit"
  },
  {
    "Result": "Skeleton",
    "Parent1": "Leery Lout",
    "Parent2": "Firespirit"
  },
  {
    "Result": "Skeleton Soldier",
    "Parent1": "Skeleton",
    "Parent2": "Restless Armour"
  },
  {
    "Result": "Skeleton Soldier",
    "Parent1": "Undead Family (E)",
    "Parent2": "Demon Family (E)"
  },
  {
    "Result": "Skipper",
    "Parent1": "Winky",
    "Parent2": "Pan Piper"
  },
  {
    "Result": "Skullrider",
    "Parent1": "Dragon Family (F)",
    "Parent2": "Undead Family (F)"
  },
  {
    "Result": "Skullrider",
    "Parent1": "Skeleton",
    "Parent2": "Killer Gila"
  },
  {
    "Result": "Slick Slime",
    "Parent1": "Bubble Slime",
    "Parent2": "Box Slime"
  },
  {
    "Result": "Slime Knight",
    "Parent1": "Slime Stack",
    "Parent2": "Leery Lout"
  },
  {
    "Result": "Slime Stack",
    "Parent1": "Slime Family (F)",
    "Parent2": "Material Family (F)"
  },
  {
    "Result": "Slimeshroom",
    "Parent1": "Slime Family (G)",
    "Parent2": "Undead Family (G)"
  },
  {
    "Result": "Small Fry",
    "Parent1": "Slime Family (G)",
    "Parent2": "Dragon Family (G)"
  },
  {
    "Result": "Snail Slime",
    "Parent1": "Shell Slime",
    "Parent2": "Mad Mollusk"
  },
  {
    "Result": "Snowmangler",
    "Parent1": "Slime Family (F)",
    "Parent2": "Undead Family (F)"
  },
  {
    "Result": "Soft Serve Spook",
    "Parent1": "Slime Family (G)",
    "Parent2": "Undead Family (G)"
  },
  {
    "Result": "Spiked Hare",
    "Parent1": "Bunicorn",
    "Parent2": "Napir"
  },
  {
    "Result": "Spiny Slime",
    "Parent1": "Slime Family (E)",
    "Parent2": "Beast Family (E)"
  },
  {
    "Result": "Spiny Slime",
    "Parent1": "Snowmangler",
    "Parent2": "Disfigurine"
  },
  {
    "Result": "Spitnik",
    "Parent1": "Demon Family (G)",
    "Parent2": "Material Family (G)"
  },
  {
    "Result": "Spitzfire",
    "Parent1": "Pteranodon",
    "Parent2": "Foo Dog"
  },
  {
    "Result": "Splatypunk",
    "Parent1": "Beast Family (E)",
    "Parent2": "Nature Family (E)"
  },
  {
    "Result": "Splatypunk",
    "Parent1": "Platypunk",
    "Parent2": "Guaardvark"
  },
  {
    "Result": "Stabosaur",
    "Parent1": "Dragon Family (E)",
    "Parent2": "Material Family (E)"
  },
  {
    "Result": "Stabosaur",
    "Parent1": "Erazor Blade",
    "Parent2": "Nardragon"
  },
  {
    "Result": "Stark Raven",
    "Parent1": "Nature Family (G)",
    "Parent2": "Undead Family (G)"
  },
  {
    "Result": "String Fella",
    "Parent1": "Bag o' Laughs",
    "Parent2": "Leery Lout"
  },
  {
    "Result": "Stump Chump",
    "Parent1": "Nature Family (G)",
    "Parent2": "Undead Family (G)"
  },
  {
    "Result": "Succubat",
    "Parent1": "Demon Family (F)",
    "Parent2": "Beast Family (F)"
  },
  {
    "Result": "Suckling Ocker",
    "Parent1": "Khalamari Kid",
    "Parent2": "Khalamari Kid"
  },
  {
    "Result": "Sugarstar Slime",
    "Parent1": "Spiny Slime",
    "Parent2": "Fromage Fray"
  },
  {
    "Result": "Sunset Sultan",
    "Parent1": "Vampire Cat",
    "Parent2": "Spitnik"
  },
  {
    "Result": "Teeny Sanguini",
    "Parent1": "??? Family (A)",
    "Parent2": "??? Family (A)"
  },
  {
    "Result": "Teeny Sanguini",
    "Parent1": "Demon Family (G)",
    "Parent2": "Beast Family (G)"
  },
  {
    "Result": "Toady",
    "Parent1": "Bunicorn",
    "Parent2": "Khalamari Kid"
  },
  {
    "Result": "Tortoceratops",
    "Parent1": "Armoured Wartoise",
    "Parent2": "Drag Racer"
  },
  {
    "Result": "Vampire Cat",
    "Parent1": "Beast Family (F)",
    "Parent2": "Dragon Family (F)"
  },
  {
    "Result": "Vampire Cat",
    "Parent1": "Candy Cat",
    "Parent2": "Mouseflap"
  },
  {
    "Result": "Vegandragora",
    "Parent1": "Fright Bulb",
    "Parent2": "Damselfly"
  },
  {
    "Result": "Walking Corpse",
    "Parent1": "Beast Family (F)",
    "Parent2": "Undead Family (F)"
  },
  {
    "Result": "Walking Corpse",
    "Parent1": "Putrefido",
    "Parent2": "Skeleton"
  },
  {
    "Result": "Wax Murderer",
    "Parent1": "Undead Family (G)",
    "Parent2": "Material Family (G)"
  },
  {
    "Result": "Weaken Beakon",
    "Parent1": "Bullfinch",
    "Parent2": "Putrefido"
  },
  {
    "Result": "Weartiger",
    "Parent1": "Mummy Boy",
    "Parent2": "Beast Family (Any)"
  },
  {
    "Result": "Well Wisher",
    "Parent1": "Material Family (E)",
    "Parent2": "Dragon Family (E)"
  },
  {
    "Result": "Whizzard",
    "Parent1": "Blinkster",
    "Parent2": "Lump Wizard"
  },
  {
    "Result": "Wing Slime",
    "Parent1": "Slime Family (G)",
    "Parent2": "Dragon Family (G)"
  },
  {
    "Result": "Winky",
    "Parent1": "String Fella",
    "Parent2": "Lunatick"
  },
  {
    "Result": "Woebergine",
    "Parent1": "Fright Bulb",
    "Parent2": "Ornery Onion"
  },
  {
    "Result": "Wyrtle",
    "Parent1": "Armoured Wartoise",
    "Parent2": "Flython"
  },
  {
    "Result": "Wyrtle",
    "Parent1": "Armoured Wartoise",
    "Parent2": "Beast Family (Any)"
  },
  {
    "Result": "Wyrtle",
    "Parent1": "Dragon Family (E)",
    "Parent2": "Slime Family (E)"
  }
]